[
  {
    "model": "crm.LandScoreChemical",
    "fields": {
      "id":1,
      "ec":5,
      "nh4n":7,
      "no3n":4,
      "total_nitrogen":3,
      "nh4_per_nitrogen":1,
      "ph":1.0,
      "cao":10,
      "mgo":6,
      "k2o":5,
      "base_saturation":1.0,
      "cao_per_mgo":2.0,
      "mgo_per_k2o":1.0,
      "phosphorus_absorption":2,
      "p2o5":3,
      "cec":3,
      "humus":1.0,
      "bulk_density":1.0,
      "remark":null,
      "land_id":1,
      "area_id":1,
      "period_id":2,
      "ledger_id": 2,
      "created_at":"2022-08-13",
      "updated_at":null
    }
  },
  {
    "model": "crm.LandScoreChemical",
    "fields": {
      "id":2,
      "ec":10,
      "nh4n":8,
      "no3n":8,
      "total_nitrogen":10,
      "nh4_per_nitrogen":4,
      "ph":1.0,
      "cao":2,
      "mgo":1,
      "k2o":3,
      "base_saturation":2.0,
      "cao_per_mgo":1.0,
      "mgo_per_k2o":1.0,
      "phosphorus_absorption":6,
      "p2o5":3,
      "cec":5,
      "humus":1.0,
      "bulk_density":1.0,
      "remark":null,
      "land_id":1,
      "area_id":2,
      "period_id":2,
      "ledger_id": 2,
      "created_at":"2022-08-13",
      "updated_at":null
    }
  },
  {
    "model": "crm.LandScoreChemical",
    "fields": {
      "id":3,
      "ec":3,
      "nh4n":2,
      "no3n":5,
      "total_nitrogen":7,
      "nh4_per_nitrogen":6,
      "ph":1.0,
      "cao":7,
      "mgo":7,
      "k2o":2,
      "base_saturation":1.0,
      "cao_per_mgo":1.0,
      "mgo_per_k2o":2.0,
      "phosphorus_absorption":6,
      "p2o5":8,
      "cec":8,
      "humus":2.0,
      "bulk_density":2.0,
      "remark":null,
      "land_id":1,
      "area_id":3,
      "period_id":2,
      "ledger_id": 2,
      "created_at":"2022-08-13",
      "updated_at":null
    }
  },
  {
    "model": "crm.LandScoreChemical",
    "fields": {
      "id":4,
      "ec":9,
      "nh4n":8,
      "no3n":4,
      "total_nitrogen":8,
      "nh4_per_nitrogen":10,
      "ph":1.0,
      "cao":9,
      "mgo":8,
      "k2o":2,
      "base_saturation":1.0,
      "cao_per_mgo":2.0,
      "mgo_per_k2o":1.0,
      "phosphorus_absorption":10,
      "p2o5":6,
      "cec":7,
      "humus":2.0,
      "bulk_density":2.0,
      "remark":null,
      "land_id":1,
      "area_id":4,
      "period_id":2,
      "ledger_id": 2,
      "created_at":"2022-08-13",
      "updated_at":null
    }
  },
  {
    "model": "crm.LandScoreChemical",
    "fields": {
      "id":5,
      "ec":5,
      "nh4n":2,
      "no3n":10,
      "total_nitrogen":10,
      "nh4_per_nitrogen":5,
      "ph":2.0,
      "cao":10,
      "mgo":5,
      "k2o":6,
      "base_saturation":2.0,
      "cao_per_mgo":1.0,
      "mgo_per_k2o":2.0,
      "phosphorus_absorption":2,
      "p2o5":9,
      "cec":1,
      "humus":2.0,
      "bulk_density":1.0,
      "remark":null,
      "land_id":1,
      "area_id":5,
      "period_id":2,
      "ledger_id": 2,
      "created_at":"2022-08-13",
      "updated_at":null
    }
  },
  {
    "model": "crm.LandScoreChemical",
    "fields": {
      "id":6,
      "ec":3,
      "nh4n":8,
      "no3n":6,
      "total_nitrogen":8,
      "nh4_per_nitrogen":9,
      "ph":1.0,
      "cao":2,
      "mgo":10,
      "k2o":3,
      "base_saturation":2.0,
      "cao_per_mgo":2.0,
      "mgo_per_k2o":2.0,
      "phosphorus_absorption":10,
      "p2o5":5,
      "cec":1,
      "humus":2.0,
      "bulk_density":1.0,
      "remark":null,
      "land_id":1,
      "area_id":6,
      "period_id":2,
      "ledger_id": 2,
      "created_at":"2022-08-13",
      "updated_at":null
    }
  },
  {
    "model": "crm.LandScoreChemical",
    "fields": {
      "id":7,
      "ec":1,
      "nh4n":2,
      "no3n":2,
      "total_nitrogen":7,
      "nh4_per_nitrogen":8,
      "ph":2.0,
      "cao":9,
      "mgo":5,
      "k2o":3,
      "base_saturation":2.0,
      "cao_per_mgo":1.0,
      "mgo_per_k2o":1.0,
      "phosphorus_absorption":9,
      "p2o5":7,
      "cec":4,
      "humus":1.0,
      "bulk_density":1.0,
      "remark":null,
      "land_id":1,
      "area_id":7,
      "period_id":2,
      "ledger_id": 2,
      "created_at":"2022-08-13",
      "updated_at":null
    }
  },
  {
    "model": "crm.LandScoreChemical",
    "fields": {
      "id":8,
      "ec":5,
      "nh4n":8,
      "no3n":5,
      "total_nitrogen":6,
      "nh4_per_nitrogen":5,
      "ph":1.0,
      "cao":10,
      "mgo":1,
      "k2o":3,
      "base_saturation":1.0,
      "cao_per_mgo":2.0,
      "mgo_per_k2o":1.0,
      "phosphorus_absorption":7,
      "p2o5":3,
      "cec":10,
      "humus":2.0,
      "bulk_density":2.0,
      "remark":null,
      "land_id":1,
      "area_id":8,
      "period_id":2,
      "ledger_id": 2,
      "created_at":"2022-08-13",
      "updated_at":null
    }
  },
  {
    "model": "crm.LandScoreChemical",
    "fields": {
      "id":9,
      "ec":10,
      "nh4n":2,
      "no3n":9,
      "total_nitrogen":8,
      "nh4_per_nitrogen":1,
      "ph":2.0,
      "cao":6,
      "mgo":7,
      "k2o":3,
      "base_saturation":2.0,
      "cao_per_mgo":1.0,
      "mgo_per_k2o":2.0,
      "phosphorus_absorption":7,
      "p2o5":3,
      "cec":4,
      "humus":1.0,
      "bulk_density":1.0,
      "remark":null,
      "land_id":1,
      "area_id":9,
      "period_id":2,
      "ledger_id": 2,
      "created_at":"2022-08-13",
      "updated_at":null
    }
  },
  {
    "model": "crm.LandScoreChemical",
    "fields": {
      "id":10,
      "ec":8,
      "nh4n":8,
      "no3n":10,
      "total_nitrogen":6,
      "nh4_per_nitrogen":10,
      "ph":2.0,
      "cao":10,
      "mgo":3,
      "k2o":6,
      "base_saturation":2.0,
      "cao_per_mgo":1.0,
      "mgo_per_k2o":1.0,
      "phosphorus_absorption":3,
      "p2o5":3,
      "cec":7,
      "humus":2.0,
      "bulk_density":2.0,
      "remark":null,
      "land_id":2,
      "area_id":1,
      "period_id":2,
      "ledger_id": 1,
      "created_at":"2022-08-13",
      "updated_at":null
    }
  },
  {
    "model": "crm.LandScoreChemical",
    "fields": {
      "id":11,
      "ec":9,
      "nh4n":9,
      "no3n":4,
      "total_nitrogen":7,
      "nh4_per_nitrogen":1,
      "ph":2.0,
      "cao":1,
      "mgo":1,
      "k2o":3,
      "base_saturation":2.0,
      "cao_per_mgo":2.0,
      "mgo_per_k2o":1.0,
      "phosphorus_absorption":4,
      "p2o5":8,
      "cec":10,
      "humus":2.0,
      "bulk_density":2.0,
      "remark":null,
      "land_id":2,
      "area_id":2,
      "period_id":2,
      "ledger_id": 1,
      "created_at":"2022-08-13",
      "updated_at":null
    }
  },
  {
    "model": "crm.LandScoreChemical",
    "fields": {
      "id":12,
      "ec":6,
      "nh4n":7,
      "no3n":8,
      "total_nitrogen":7,
      "nh4_per_nitrogen":8,
      "ph":1.0,
      "cao":4,
      "mgo":9,
      "k2o":9,
      "base_saturation":2.0,
      "cao_per_mgo":1.0,
      "mgo_per_k2o":1.0,
      "phosphorus_absorption":10,
      "p2o5":7,
      "cec":8,
      "humus":1.0,
      "bulk_density":1.0,
      "remark":null,
      "land_id":2,
      "area_id":3,
      "period_id":2,
      "ledger_id": 1,
      "created_at":"2022-08-13",
      "updated_at":null
    }
  },
  {
    "model": "crm.LandScoreChemical",
    "fields": {
      "id":13,
      "ec":9,
      "nh4n":6,
      "no3n":9,
      "total_nitrogen":1,
      "nh4_per_nitrogen":1,
      "ph":1.0,
      "cao":2,
      "mgo":5,
      "k2o":5,
      "base_saturation":1.0,
      "cao_per_mgo":2.0,
      "mgo_per_k2o":1.0,
      "phosphorus_absorption":9,
      "p2o5":2,
      "cec":10,
      "humus":2.0,
      "bulk_density":1.0,
      "remark":null,
      "land_id":2,
      "area_id":4,
      "period_id":2,
      "ledger_id": 1,
      "created_at":"2022-08-13",
      "updated_at":null
    }
  },
  {
    "model": "crm.LandScoreChemical",
    "fields": {
      "id":14,
      "ec":10,
      "nh4n":1,
      "no3n":10,
      "total_nitrogen":9,
      "nh4_per_nitrogen":2,
      "ph":1.0,
      "cao":5,
      "mgo":9,
      "k2o":5,
      "base_saturation":1.0,
      "cao_per_mgo":1.0,
      "mgo_per_k2o":1.0,
      "phosphorus_absorption":6,
      "p2o5":1,
      "cec":7,
      "humus":1.0,
      "bulk_density":2.0,
      "remark":null,
      "land_id":2,
      "area_id":5,
      "period_id":2,
      "ledger_id": 1,
      "created_at":"2022-08-13",
      "updated_at":null
    }
  },
  {
    "model": "crm.LandScoreChemical",
    "fields": {
      "id":15,
      "ec":2,
      "nh4n":1,
      "no3n":3,
      "total_nitrogen":9,
      "nh4_per_nitrogen":2,
      "ph":2.0,
      "cao":8,
      "mgo":3,
      "k2o":4,
      "base_saturation":2.0,
      "cao_per_mgo":2.0,
      "mgo_per_k2o":2.0,
      "phosphorus_absorption":9,
      "p2o5":9,
      "cec":5,
      "humus":1.0,
      "bulk_density":2.0,
      "remark":null,
      "land_id":2,
      "area_id":6,
      "period_id":2,
      "ledger_id": 1,
      "created_at":"2022-08-13",
      "updated_at":null
    }
  },
  {
    "model": "crm.LandScoreChemical",
    "fields": {
      "id":16,
      "ec":10,
      "nh4n":7,
      "no3n":2,
      "total_nitrogen":5,
      "nh4_per_nitrogen":8,
      "ph":1.0,
      "cao":8,
      "mgo":6,
      "k2o":6,
      "base_saturation":2.0,
      "cao_per_mgo":1.0,
      "mgo_per_k2o":2.0,
      "phosphorus_absorption":5,
      "p2o5":3,
      "cec":1,
      "humus":1.0,
      "bulk_density":2.0,
      "remark":null,
      "land_id":2,
      "area_id":7,
      "period_id":2,
      "ledger_id": 1,
      "created_at":"2022-08-13",
      "updated_at":null
    }
  },
  {
    "model": "crm.LandScoreChemical",
    "fields": {
      "id":17,
      "ec":9,
      "nh4n":10,
      "no3n":5,
      "total_nitrogen":6,
      "nh4_per_nitrogen":10,
      "ph":2.0,
      "cao":10,
      "mgo":10,
      "k2o":9,
      "base_saturation":2.0,
      "cao_per_mgo":1.0,
      "mgo_per_k2o":2.0,
      "phosphorus_absorption":6,
      "p2o5":7,
      "cec":1,
      "humus":2.0,
      "bulk_density":1.0,
      "remark":null,
      "land_id":2,
      "area_id":8,
      "period_id":2,
      "ledger_id": 1,
      "created_at":"2022-08-13",
      "updated_at":null
    }
  },
  {
    "model": "crm.LandScoreChemical",
    "fields": {
      "id":18,
      "ec":10,
      "nh4n":1,
      "no3n":5,
      "total_nitrogen":5,
      "nh4_per_nitrogen":5,
      "ph":1.0,
      "cao":1,
      "mgo":6,
      "k2o":1,
      "base_saturation":1.0,
      "cao_per_mgo":1.0,
      "mgo_per_k2o":1.0,
      "phosphorus_absorption":3,
      "p2o5":6,
      "cec":6,
      "humus":2.0,
      "bulk_density":1.0,
      "remark":null,
      "land_id":2,
      "area_id":9,
      "period_id":2,
      "ledger_id": 1,
      "created_at":"2022-08-13",
      "updated_at":null
    }
  }
]
